kakao_address/__init__.py
kakao_address/models.py
kakao_address/widgets.py
django_kakao_address-0.1.3.dist-info/LICENSE
django_kakao_address-0.1.3.dist-info/METADATA
django_kakao_address-0.1.3.dist-info/WHEEL
django_kakao_address-0.1.3.dist-info/top_level.txt
django_kakao_address-0.1.3.dist-info/zip-safe
django_kakao_address-0.1.3.dist-info/RECORD
